onsager_coefficients/__init__.py
onsager_coefficients/modifier.py
onsager_coefficients/onsager.py
onsager_coefficients-1.0.0.dist-info/METADATA
onsager_coefficients-1.0.0.dist-info/WHEEL
onsager_coefficients-1.0.0.dist-info/top_level.txt
onsager_coefficients-1.0.0.dist-info/RECORD
