Metadata-Version: 2.1
Name: onsager-coefficients
Version: 1.0.0
Home-page: https://github.com/jwjeffr/onsager_coefficients
Author: Jacob Jeffries
Author-email: jwjeffr@clemson.edu
